txBreezeChMS-1.0.5.dist-info/DESCRIPTION.rst
txBreezeChMS-1.0.5.dist-info/METADATA
txBreezeChMS-1.0.5.dist-info/RECORD
txBreezeChMS-1.0.5.dist-info/WHEEL
txBreezeChMS-1.0.5.dist-info/metadata.json
txBreezeChMS-1.0.5.dist-info/top_level.txt
txbreeze/__init__.py
txbreeze/breeze.py
txbreeze/utils.py
