Metadata-Version: 2.0
Name: txBreezeChMS
Version: 1.0.5
Summary: Twisted Python interface to BreezeChMS REST API.
Home-page: http://www.github.com/aortiz32/pyBreezeChMS/
Author: Trenton Broughton
Author-email: engineering@kindrid.com
License: Apache 2.0
Keywords: breezechms breezeapi twisted python breeze
Platform: UNKNOWN
Classifier: Development Status :: 4 - Beta
Classifier: Environment :: Console
Classifier: Intended Audience :: Developers
Classifier: License :: OSI Approved :: Apache Software License
Classifier: Operating System :: OS Independent
Classifier: Programming Language :: Python :: 2.6
Classifier: Programming Language :: Python :: 2.7
Classifier: Natural Language :: English
Requires-Dist: treq
